Metadata-Version: 2.2
Name: imeme
Version: 0.0.0
Summary: Memes collection & analysis.
Home-page: https://github.com/lycantropos/imeme/
Download-URL: https://github.com/lycantropos/imeme/archive/master.zip
Author-email: Azat Ibrakov <azatibrakov@gmail.com>
Classifier: License :: OSI Approved :: MIT License
Classifier: Programming Language :: Python :: 3.10
Classifier: Programming Language :: Python :: 3.11
Classifier: Programming Language :: Python :: 3.12
Classifier: Programming Language :: Python :: Implementation :: CPython
Classifier: Programming Language :: Python :: Implementation :: PyPy
Classifier: Programming Language :: Python :: Implementation :: CPython
Classifier: Programming Language :: Python :: Implementation :: PyPy
Requires-Python: >=3.10
Provides-Extra: tests
Requires-Dist: hypothesis<7.0,>=6.88.3; extra == "tests"
Requires-Dist: pytest<8.0,>=7.4.3; extra == "tests"
Dynamic: download-url
Dynamic: home-page
